enhancedschemathesis/.vscode/settings.json
enhancedschemathesis/__init__.py
enhancedschemathesis/_compat.py
enhancedschemathesis/_hypothesis.py
enhancedschemathesis/checks.py
enhancedschemathesis/cli/__init__.py
enhancedschemathesis/cli/callbacks.py
enhancedschemathesis/cli/context.py
enhancedschemathesis/cli/options.py
enhancedschemathesis/cli/output/__init__.py
enhancedschemathesis/cli/output/default.py
enhancedschemathesis/cli/output/short.py
enhancedschemathesis/constants.py
enhancedschemathesis/converter.py
enhancedschemathesis/exceptions.py
enhancedschemathesis/extra/__init__.py
enhancedschemathesis/extra/_aiohttp.py
enhancedschemathesis/extra/pytest_plugin.py
enhancedschemathesis/filters.py
enhancedschemathesis/hooks.py
enhancedschemathesis/lazy.py
enhancedschemathesis/loaders.py
enhancedschemathesis/models.py
enhancedschemathesis/runner/__init__.py
enhancedschemathesis/runner/events.py
enhancedschemathesis/runner/impl/__init__.py
enhancedschemathesis/runner/impl/core.py
enhancedschemathesis/runner/impl/solo.py
enhancedschemathesis/runner/impl/threadpool.py
enhancedschemathesis/runner/serialization.py
enhancedschemathesis/schemas.py
enhancedschemathesis/spec_schemas.py
enhancedschemathesis/store_result.py
enhancedschemathesis/types.py
enhancedschemathesis/utils.py
enhancedschemathesis-1.0.2.dist-info/entry_points.txt
enhancedschemathesis-1.0.2.dist-info/LICENSE
enhancedschemathesis-1.0.2.dist-info/WHEEL
enhancedschemathesis-1.0.2.dist-info/METADATA
enhancedschemathesis-1.0.2.dist-info/RECORD
