Metadata-Version: 2.1
Name: enhancedschemathesis
Version: 1.0.2
Summary: Hypothesis strategies for Open API / Swagger schemas
Home-page: https://github.com/arvindjangra1996/schemathesis
License: MIT
Keywords: testing
Author: arvind
Author-email: arvind@sentieo.com
Requires-Python: >=3.6,<4.0
Classifier: Development Status :: 5 - Production/Stable
Classifier: Environment :: Console
Classifier: Framework :: Hypothesis
Classifier: Framework :: Pytest
Classifier: Intended Audience :: Developers
Classifier: License :: OSI Approved :: MIT License
Classifier: Operating System :: OS Independent
Classifier: Programming Language :: Python :: 3
Classifier: Programming Language :: Python :: 3 :: Only
Classifier: Programming Language :: Python :: 3.6
Classifier: Programming Language :: Python :: 3.7
Classifier: Programming Language :: Python :: 3.8
Classifier: Programming Language :: Python :: Implementation :: CPython
Classifier: Topic :: Software Development :: Testing
Requires-Dist: attrs (>=19.1,<20.0)
Requires-Dist: click (>=7.0,<8.0)
Requires-Dist: hypothesis (>=4.32,<6.0)
Requires-Dist: hypothesis_jsonschema (>=0.9.13,<1.0)
Requires-Dist: importlib_metadata (>=1.1,<2.0); python_version < "3.8"
Requires-Dist: jsonschema (>=3.0.0,<4.0.0)
Requires-Dist: pytest (>4.6.4)
Requires-Dist: pytest-subtests (>=0.2.1,<0.3.0)
Requires-Dist: pyyaml (>=5.1,<6.0)
Requires-Dist: requests (>=2.22,<3.0)
Requires-Dist: werkzeug (>0.16.0)
Project-URL: Repository, https://github.com/arvindjangra1996/schemathesis
